em/__init__.py
em/__main__.py
em/_version.py
em/cli.py
em/emojis.json
em_keyboard-5.3.0.dist-info/METADATA
em_keyboard-5.3.0.dist-info/WHEEL
em_keyboard-5.3.0.dist-info/entry_points.txt
em_keyboard-5.3.0.dist-info/licenses/LICENSE
em_keyboard-5.3.0.dist-info/RECORD
