Metadata-Version: 2.4
Name: em-keyboard
Version: 5.3.0
Summary: The CLI Emoji Keyboard
Project-URL: Changelog, https://github.com/hugovk/em-keyboard/releases
Project-URL: Homepage, https://github.com/hugovk/em-keyboard
Project-URL: Source, https://github.com/hugovk/em-keyboard
Author-email: Kenneth Reitz <me@kennethreitz.org>
Maintainer: Hugo van Kemenade
License-Expression: ISC
License-File: LICENSE
Keywords: CLI,emoji,keyboard,search
Classifier: Development Status :: 5 - Production/Stable
Classifier: Intended Audience :: Developers
Classifier: Natural Language :: English
Classifier: Programming Language :: Python
Classifier: Programming Language :: Python :: 3 :: Only
Classifier: Programming Language :: Python :: 3.10
Classifier: Programming Language :: Python :: 3.11
Classifier: Programming Language :: Python :: 3.12
Classifier: Programming Language :: Python :: 3.13
Classifier: Programming Language :: Python :: 3.14
Classifier: Programming Language :: Python :: Implementation :: CPython
Classifier: Programming Language :: Python :: Implementation :: PyPy
Requires-Python: >=3.10
Requires-Dist: pyperclip
Provides-Extra: tests
Requires-Dist: pytest; extra == 'tests'
Requires-Dist: pytest-cov; extra == 'tests'
